Workbook

Sheet Assumptions
A1: BoardIQ — Financial Model Assumptions
B3: Year 1 | C3: Year 2 | D3: Year 3 | E3: Year 4 | F3: Year 5
A5: Building Growth
A6: Buildings (end of year) | B6: 50 | C6: 125 | D6: 250 | E6: 400 | F6: 500
A7: New buildings added | B7: =B6 -> 50 | C7: =C6-B6 -> 75 | D7: =D6-C6 -> 125 | E7: =E6-D6 -> 150 | F7: =F6-E6 -> 100
A8: Building monthly fee | B8: 50 | C8: 50 | D8: 50 | E8: 50 | F8: 50
A9: Building annual churn rate | B9: 0.05 | C9: 0.05 | D9: 0.08 | E9: 0.08 | F9: 0.1
A11: Vendor Growth
A12: Vendors (end of year) | B12: 15 | C12: 25 | D12: 50 | E12: 75 | F12: 100
A13: Vendor annual fee | B13: 250 | C13: 250 | D13: 250 | E13: 250 | F13: 250
A14: Vendor annual churn rate | B14: 0.1 | C14: 0.1 | D14: 0.1 | E14: 0.1 | F14: 0.1
A17: Infrastructure (Monthly)
A18: Hosting (Railway/AWS) | B18: 25 | C18: 50 | D18: 100 | E18: 150 | F18: 200
A19: PostgreSQL | B19: 10 | C19: 25 | D19: 50 | E19: 75 | F19: 100
A20: S3 file storage | B20: 5 | C20: 10 | D20: 20 | E20: 30 | F20: 40
A21: Anthropic API (Claude) | B21: 30 | C21: 80 | D21: 200 | E21: 350 | F21: 500
A22: Email (SendGrid) | B22: 0 | C22: 15 | D22: 20 | E22: 25 | F22: 30
A23: Domain + SSL | B23: 1 | C23: 1 | D23: 1 | E23: 1 | F23: 1
A24: Monitoring / logging | B24: 0 | C24: 10 | D24: 25 | E24: 40 | F24: 50
A25: Total monthly infra | B25: =SUM(B18:B24) -> 71 | C25: =SUM(C18:C24) -> 191 | D25: =SUM(D18:D24) -> 416 | E25: =SUM(E18:E24) -> 671 | F25: =SUM(F18:F24) -> 921
A27: People (Annual Salary / Cost)
A28: AI-assisted developer (contract) | B28: 0 | C28: 60000 | D28: 90000 | E28: 90000 | F28: 120000
A29: Founder salary | B29: 0 | C29: 0 | D29: 60000 | E29: 80000 | F29: 100000
A30: Sales / BD (part-time → full) | B30: 0 | C30: 0 | D30: 40000 | E30: 70000 | F30: 85000
A31: Customer success | B31: 0 | C31: 0 | D31: 0 | E31: 50000 | F31: 55000
A32: Total annual people cost | B32: =SUM(B28:B31) -> 0 | C32: =SUM(C28:C31) -> 60000 | D32: =SUM(D28:D31) -> 190000 | E32: =SUM(E28:E31) -> 290000 | F32: =SUM(F28:F31) -> 360000

Sheet P&L
A1: BoardIQ — 5-Year Profit & Loss
B3: Year 1 | C3: Year 2 | D3: Year 3 | E3: Year 4 | F3: Year 5
A5: Revenue
A6: Building revenue (monthly × 12) | B6: =(Assumptions!B6/2)*Assumptions!B8*12 -> 15000 | C6: =((Assumptions!B6+Assumptions!C6)/2)*Assumptions!C8*12 -> 52500 | D6: =((Assumptions!C6+Assumptions!D6)/2)*Assumptions!D8*12 -> 112500 | E6: =((Assumptions!D6+Assumptions!E6)/2)*Assumptions!E8*12 -> 195000 | F6: =((Assumptions!E6+Assumptions!F6)/2)*Assumptions!F8*12 -> 270000
A7: Less: building churn | B7: =-B6*Assumptions!B9 -> -750 | C7: =-C6*Assumptions!C9 -> -2625 | D7: =-D6*Assumptions!D9 -> -9000 | E7: =-E6*Assumptions!E9 -> -15600 | F7: =-F6*Assumptions!F9 -> -27000
A8: Net building revenue | B8: =B6+B7 -> 14250 | C8: =C6+C7 -> 49875 | D8: =D6+D7 -> 103500 | E8: =E6+E7 -> 179400 | F8: =F6+F7 -> 243000
A9: Vendor revenue (annual fee) | B9: =(Assumptions!B12/2)*Assumptions!B13 -> 1875 | C9: =((Assumptions!B12+Assumptions!C12)/2)*Assumptions!C13 -> 5000 | D9: =((Assumptions!C12+Assumptions!D12)/2)*Assumptions!D13 -> 9375 | E9: =((Assumptions!D12+Assumptions!E12)/2)*Assumptions!E13 -> 15625 | F9: =((Assumptions!E12+Assumptions!F12)/2)*Assumptions!F13 -> 21875
A10: Less: vendor churn | B10: =-B9*Assumptions!B14 -> -187.5 | C10: =-C9*Assumptions!C14 -> -500 | D10: =-D9*Assumptions!D14 -> -937.5 | E10: =-E9*Assumptions!E14 -> -1562.5 | F10: =-F9*Assumptions!F14 -> -2187.5
A11: Net vendor revenue | B11: =B9+B10 -> 1687.5 | C11: =C9+C10 -> 4500 | D11: =D9+D10 -> 8437.5 | E11: =E9+E10 -> 14062.5 | F11: =F9+F10 -> 19687.5
A12: Total Revenue | B12: =B8+B11 -> 15937.5 | C12: =C8+C11 -> 54375 | D12: =D8+D11 -> 111937.5 | E12: =E8+E11 -> 193462.5 | F12: =F8+F11 -> 262687.5
A14: Costs
A15: Infrastructure (annual) | B15: =Assumptions!B25*12 -> 852 | C15: =Assumptions!C25*12 -> 2292 | D15: =Assumptions!D25*12 -> 4992 | E15: =Assumptions!E25*12 -> 8052 | F15: =Assumptions!F25*12 -> 11052
A16: People costs | B16: =Assumptions!B32 -> 0 | C16: =Assumptions!C32 -> 60000 | D16: =Assumptions!D32 -> 190000 | E16: =Assumptions!E32 -> 290000 | F16: =Assumptions!F32 -> 360000
A17: Software / tools | B17: 500 | C17: 1200 | D17: 2400 | E17: 3600 | F17: 4800
A18: Legal / accounting | B18: 2000 | C18: 3000 | D18: 5000 | E18: 8000 | F18: 10000
A19: Marketing / sales | B19: 1000 | C19: 5000 | D19: 15000 | E19: 25000 | F19: 40000
A20: Total Costs | B20: =SUM(B15:B19) -> 4352 | C20: =SUM(C15:C19) -> 71492 | D20: =SUM(D15:D19) -> 217392 | E20: =SUM(E15:E19) -> 334652 | F20: =SUM(F15:F19) -> 425852
A22: Profitability
A23: Gross Profit | B23: =B12-B20 -> 11585.5 | C23: =C12-C20 -> -17117 | D23: =D12-D20 -> -105454.5 | E23: =E12-E20 -> -141189.5 | F23: =F12-F20 -> -163164.5
A24: Gross Margin | B24: =IF(B12=0,0,B23/B12) -> 0.72693333 | C24: =IF(C12=0,0,C23/C12) -> -0.3147954 | D24: =IF(D12=0,0,D23/D12) -> -0.94208375 | E24: =IF(E12=0,0,E23/E12) -> -0.72980293 | F24: =IF(F12=0,0,F23/F12) -> -0.62113538
A26: Cumulative P&L | B26: =B23 -> 11585.5 | C26: =B26+C23 -> -5531.5 | D26: =C26+D23 -> -110986 | E26: =D26+E23 -> -252175.5 | F26: =E26+F23 -> -415340
A28: Key Metrics
A29: Revenue per building (annual) | B29: =IF(Assumptions!B6=0,0,B12/Assumptions!B6) -> 318.75 | C29: =IF(Assumptions!C6=0,0,C12/Assumptions!C6) -> 435 | D29: =IF(Assumptions!D6=0,0,D12/Assumptions!D6) -> 447.75 | E29: =IF(Assumptions!E6=0,0,E12/Assumptions!E6) -> 483.65625 | F29: =IF(Assumptions!F6=0,0,F12/Assumptions!F6) -> 525.375
A30: Cost per building (annual) | B30: =IF(Assumptions!B6=0,0,B20/Assumptions!B6) -> 87.04 | C30: =IF(Assumptions!C6=0,0,C20/Assumptions!C6) -> 571.936 | D30: =IF(Assumptions!D6=0,0,D20/Assumptions!D6) -> 869.568 | E30: =IF(Assumptions!E6=0,0,E20/Assumptions!E6) -> 836.63 | F30: =IF(Assumptions!F6=0,0,F20/Assumptions!F6) -> 851.704
A31: LTV per building (3yr, no churn adj) | B31: =B29*3 -> 956.25 | C31: =C29*3 -> 1305 | D31: =D29*3 -> 1343.25 | E31: =E29*3 -> 1450.9688 | F31: =F29*3 -> 1576.125
A32: CAC estimate | B32: =IF(Assumptions!B7=0,0,B19/Assumptions!B7) -> 20 | C32: =IF(Assumptions!C7=0,0,C19/Assumptions!C7) -> 66.666667 | D32: =IF(Assumptions!D7=0,0,D19/Assumptions!D7) -> 120 | E32: =IF(Assumptions!E7=0,0,E19/Assumptions!E7) -> 166.66667 | F32: =IF(Assumptions!F7=0,0,F19/Assumptions!F7) -> 400
A33: LTV / CAC | B33: =IF(B32=0,0,B31/B32) -> 47.8125 | C33: =IF(C32=0,0,C31/C32) -> 19.575 | D33: =IF(D32=0,0,D31/D32) -> 11.19375 | E33: =IF(E32=0,0,E31/E32) -> 8.7058125 | F33: =IF(F32=0,0,F31/F32) -> 3.9403125
A34: Monthly burn rate | B34: =IF(B23<0,-B23/12,0) -> 0 | C34: =IF(C23<0,-C23/12,0) -> 1426.4167 | D34: =IF(D23<0,-D23/12,0) -> 8787.875 | E34: =IF(E23<0,-E23/12,0) -> 11765.792 | F34: =IF(F23<0,-F23/12,0) -> 13597.042
A35: Months of runway (if break-even) | B35: =IF(B34=0,"Profitable","-") -> Profitable | C35: =IF(C34=0,"Profitable","-") -> - | D35: =IF(D34=0,"Profitable","-") -> - | E35: =IF(E34=0,"Profitable","-") -> - | F35: =IF(F34=0,"Profitable","-") -> -

Sheet Unit Economics
A1: BoardIQ — Unit Economics at 500 Buildings
A3: Metric | B3: Monthly | C3: Annual
A5: Revenue
A6: Buildings | B6: 500
A7: Monthly fee per building | B7: 50
A8: Building MRR | B8: =B6*B7 -> 25000 | C8: =B8*12 -> 300000
A9: Vendors | B9: 100
A10: Annual fee per vendor | B10: 250
A11: Vendor MRR (annual / 12) | B11: =B9*B10/12 -> 2083.3333 | C11: =B11*12 -> 25000
A12: Total MRR | B12: =B8+B11 -> 27083.333 | C12: =B12*12 -> 325000
A13: Total ARR | C13: =C12 -> 325000
A15: Costs at 500 Buildings
A16: Hosting | B16: 200 | C16: =B16*12 -> 2400
A17: PostgreSQL | B17: 100 | C17: =B17*12 -> 1200
A18: S3 storage | B18: 40 | C18: =B18*12 -> 480
A19: Anthropic API | B19: 500 | C19: =B19*12 -> 6000
A20: Email (SendGrid) | B20: 30 | C20: =B20*12 -> 360
A21: Domain + SSL | B21: 1 | C21: =B21*12 -> 12
A22: Monitoring | B22: 50 | C22: =B22*12 -> 600
A23: Total infrastructure | B23: =SUM(B16:B22) -> 921 | C23: =B23*12 -> 11052
A25: People (Year 5)
A26: Developer (AI-assisted) | B26: =C26/12 -> 10000 | C26: 120000
A27: Founder | B27: =C27/12 -> 8333.3333 | C27: 100000
A28: Sales / BD | B28: =C28/12 -> 7083.3333 | C28: 85000
A29: Customer success | B29: =C29/12 -> 4583.3333 | C29: 55000
A30: Total people | B30: =C30/12 -> 30000 | C30: =SUM(C26:C29) -> 360000
A32: Other Costs
A33: Software / tools | B33: =C33/12 -> 400 | C33: 4800
A34: Legal / accounting | B34: =C34/12 -> 833.33333 | C34: 10000
A35: Marketing / sales | B35: =C35/12 -> 3333.3333 | C35: 40000
A36: Total other | B36: =C36/12 -> 4566.6667 | C36: =SUM(C33:C35) -> 54800
A38: Summary at Scale (500 Buildings)
A39: Total Revenue | B39: =B12 -> 27083.333 | C39: =C13 -> 325000
A40: Total Costs | B40: =B23+B30+B36 -> 35487.667 | C40: =C23+C30+C36 -> 425852
A41: Net Profit | B41: =B39-B40 -> -8404.3333 | C41: =C39-C40 -> -100852
A42: Net Margin | B42: =IF(B39=0,0,B41/B39) -> -0.31031385 | C42: =IF(C39=0,0,C41/C39) -> -0.31031385
A44: Infra cost per building | B44: =B23/B6 -> 1.842 | C44: =C23/B6 -> 22.104
A45: Total cost per building | B45: =B40/B6 -> 70.975333 | C45: =C40/B6 -> 851.704
A46: Revenue per building | B46: =B12/B6 -> 54.166667 | C46: =C13/B6 -> 650
A47: Profit per building | B47: =B41/B6 -> -16.808667 | C47: =C41/B6 -> -201.704
